Metadata-Version: 2.1
Name: marxanconpy
Version: 0.1.5rc2019090513
Summary: The python package for Marxan Connect
Home-page: https://remi-daigle.github.io/marxanconpy/
Author: Remi Daigle
Author-email: remi.daigle@dal.ca
License: UNKNOWN
Platform: UNKNOWN
Classifier: Programming Language :: Python :: 3
Classifier: License :: OSI Approved :: MIT License
Classifier: Operating System :: OS Independent
